quadcopter/__init__.py
quadcopter/__main__.py
quadcopter/controllers.py
quadcopter/dynamics.py
quadcopter/env.py
quadcopter/evaluation.py
quadcopter/gym_env.py
quadcopter/logging.py
quadcopter/plotting.py
quadcopter/simulation.py
quadcopter/utils.py
quadcopter_sim-0.3.0.dist-info/licenses/LICENSE
quadcopter_sim-0.3.0.dist-info/METADATA
quadcopter_sim-0.3.0.dist-info/WHEEL
quadcopter_sim-0.3.0.dist-info/entry_points.txt
quadcopter_sim-0.3.0.dist-info/top_level.txt
quadcopter_sim-0.3.0.dist-info/RECORD
