Metadata-Version: 2.4
Name: quadcopter-sim
Version: 0.3.0
Summary: Light‑weight quadcopter dynamics, PID control and visualisation in pure Python.
Author-email: 2black0 <2black0@gmail.com>
Maintainer-email: 2black0 <2black0@gmail.com>
License-Expression: MIT
Keywords: quadcopter,simulation,control,PID,education
Classifier: Development Status :: 3 - Alpha
Classifier: Intended Audience :: Education
Classifier: Intended Audience :: Science/Research
Classifier: Programming Language :: Python :: 3 :: Only
Classifier: Programming Language :: Python :: 3.9
Classifier: Programming Language :: Python :: 3.10
Classifier: Programming Language :: Python :: 3.11
Classifier: Topic :: Scientific/Engineering :: Physics
Classifier: Topic :: Education
Requires-Python: >=3.9
License-File: LICENSE
Requires-Dist: numpy>=1.25
Requires-Dist: scipy>=1.11
Requires-Dist: matplotlib>=3.8
Provides-Extra: dev
Requires-Dist: pytest>=8.2; extra == "dev"
Requires-Dist: pytest-cov; extra == "dev"
Requires-Dist: mypy; extra == "dev"
Requires-Dist: ruff; extra == "dev"
Requires-Dist: black; extra == "dev"
Provides-Extra: docs
Requires-Dist: sphinx; extra == "docs"
Requires-Dist: sphinx-rtd-theme; extra == "docs"
Provides-Extra: rl
Requires-Dist: gymnasium>=0.28; extra == "rl"
Provides-Extra: control
Requires-Dist: scipy>=1.11; extra == "control"
Provides-Extra: fuzzy
Requires-Dist: scikit-fuzzy; extra == "fuzzy"
Provides-Extra: data
Requires-Dist: scipy>=1.11; extra == "data"
Provides-Extra: all
Requires-Dist: pytest>=8.2; extra == "all"
Requires-Dist: pytest-cov; extra == "all"
Requires-Dist: mypy; extra == "all"
Requires-Dist: ruff; extra == "all"
Requires-Dist: black; extra == "all"
Requires-Dist: gymnasium>=0.28; extra == "all"
Requires-Dist: scikit-fuzzy; extra == "all"
Requires-Dist: scipy>=1.11; extra == "all"
Dynamic: license-file
